satelStatsPackage/__init__.py
satelStatsPackage/stats.py
statsPackage/__init__.py
statsPackage/stats.py
satelStatsPackage-0.3.dist-info/LICENSE
satelStatsPackage-0.3.dist-info/METADATA
satelStatsPackage-0.3.dist-info/WHEEL
satelStatsPackage-0.3.dist-info/top_level.txt
satelStatsPackage-0.3.dist-info/RECORD
