Metadata-Version: 2.1
Name: satelStatsPackage
Version: 0.3
Summary: This package generate statistics based on a public DB
Home-page: https://github.com/juanedomb/SATELLOGIC
Author: Juan Dombald
License: MIT
Platform: UNKNOWN
License-File: LICENSE
